cdbcli/__init__.py
cdbcli/__init__.pyc
cdbcli/commands.py
cdbcli/commands.pyc
cdbcli/completer.py
cdbcli/completer.pyc
cdbcli/environment.py
cdbcli/environment.pyc
cdbcli/grammar.py
cdbcli/grammar.pyc
cdbcli/highlighters.py
cdbcli/lexer.py
cdbcli/lexer.pyc
cdbcli/main.py
cdbcli/main.pyc
cdbcli/repl.py
cdbcli/repl.pyc
cdbcli/style.py
cdbcli/style.pyc
cdbcli/utils.py
cdbcli-0.9.1.dist-info/DESCRIPTION.rst
cdbcli-0.9.1.dist-info/METADATA
cdbcli-0.9.1.dist-info/RECORD
cdbcli-0.9.1.dist-info/WHEEL
cdbcli-0.9.1.dist-info/entry_points.txt
cdbcli-0.9.1.dist-info/metadata.json
cdbcli-0.9.1.dist-info/top_level.txt
tests/__init__.py
tests/__init__.pyc
tests/test_config.py
tests/test_grammar.py
tests/__pycache__/test_config.cpython-27-PYTEST.pyc
tests/__pycache__/test_grammar.cpython-27-PYTEST.pyc
tests/integration/__init__.py
tests/integration/fixtures.py
tests/integration/test_completer.py
tests/integration/test_repl.py
tests/unit/__init__.py
tests/unit/test_command_line.py
tests/unit/test_config.py
tests/unit/test_grammar.py
tests/unit/test_lexer.py
