Metadata-Version: 2.0
Name: cdbcli
Version: 0.9.1
Summary: Interactive command line shell for CouchDB
Home-page: https://github.com/kevinjqiu/cdbcli
Author: Kevin J. Qiu
Author-email: kevin@idempotent.ca
License: UNKNOWN
Platform: UNKNOWN
Classifier: Development Status :: 4 - Beta
Classifier: Programming Language :: Python
Classifier: Programming Language :: Python :: 3
Classifier: Programming Language :: Python :: 3.5
Classifier: Programming Language :: Python :: 3.4
Requires-Dist: CouchDB (==1.0.1)
Requires-Dist: Pygments (==2.1.3)
Requires-Dist: click (==6.6)
Requires-Dist: prompt-toolkit (==1.0.3)
